jf1uids/__init__.py
jf1uids/_finite_difference/_fluid_equations/_eigen.py
jf1uids/_finite_difference/_fluid_equations/_equations.py
jf1uids/_finite_difference/_fluid_equations/_fluxes.py
jf1uids/_finite_difference/_interface_fluxes/_weno.py
jf1uids/_finite_difference/_magnetic_update/_constrained_transport.py
jf1uids/_finite_difference/_maths/_differencing.py
jf1uids/_finite_difference/_maths/_interpolate.py
jf1uids/_finite_difference/_state_evolution/_evolve_state.py
jf1uids/_finite_difference/_time_integrators/_ssprk.py
jf1uids/_finite_difference/_timestep_estimation/_timestep_estimator.py
jf1uids/_finite_volume/_magnetic_update/_magnetic_field_update.py
jf1uids/_finite_volume/_magnetic_update/_vector_maths.py
jf1uids/_finite_volume/_riemann_solver/__init__.py
jf1uids/_finite_volume/_riemann_solver/_lax_friedrichs.py
jf1uids/_finite_volume/_riemann_solver/_riemann_solver.py
jf1uids/_finite_volume/_riemann_solver/hll.py
jf1uids/_finite_volume/_state_evolution/__init__.py
jf1uids/_finite_volume/_state_evolution/evolve_state.py
jf1uids/_finite_volume/_state_evolution/limited_gradients.py
jf1uids/_finite_volume/_state_evolution/limiters.py
jf1uids/_finite_volume/_state_evolution/reconstruction.py
jf1uids/_finite_volume/_timestep_estimation/_timestep_estimator.py
jf1uids/_fluid_equations/__init__.py
jf1uids/_fluid_equations/_equations.py
jf1uids/_fluid_equations/_fluxes.py
jf1uids/_fluid_equations/total_quantities.py
jf1uids/_geometry/__init__.py
jf1uids/_geometry/boundaries.py
jf1uids/_geometry/geometric_terms.py
jf1uids/_geometry/geometry.py
jf1uids/_physics_modules/__init__.py
jf1uids/_physics_modules/_cnn_mhd_corrector/_cnn_mhd_corrector.py
jf1uids/_physics_modules/_cnn_mhd_corrector/_cnn_mhd_corrector_options.py
jf1uids/_physics_modules/_cooling/_cooling.py
jf1uids/_physics_modules/_cooling/_cooling_tables.py
jf1uids/_physics_modules/_cooling/cooling_options.py
jf1uids/_physics_modules/_cosmic_rays/__init__.py
jf1uids-0.3.0.dist-info/METADATA
jf1uids-0.3.0.dist-info/WHEEL
jf1uids-0.3.0.dist-info/licenses/LICENSE
jf1uids-0.3.0.dist-info/RECORD
