Metadata-Version: 2.4
Name: jf1uids
Version: 0.3.0
Summary: differentiable (magneto)hydrodynamics for astrophysics in JAX
License-File: LICENSE
Author: Leonard Storcks
Requires-Python: >=3.9
Classifier: Programming Language :: Python :: 3
Classifier: Programming Language :: Python :: 3.9
Classifier: Programming Language :: Python :: 3.10
Classifier: Programming Language :: Python :: 3.11
Classifier: Programming Language :: Python :: 3.12
Classifier: Programming Language :: Python :: 3.13
Classifier: Programming Language :: Python :: 3.14
Requires-Dist: astropy (>=6.0.0)
Requires-Dist: beartype (>=0.19.0)
Requires-Dist: equinox (>=0.10.10)
Requires-Dist: jax (>=0.4.0)
Requires-Dist: numpy (>=1.0.0)
Requires-Dist: scipy (>=1.0.0)
